[{"label":"Drinks","value":"7"},{"label":"All Occasions","value":"8"},{"label":"Permanent","value":"3"},{"label":"Savoury Pie","value":"4"},{"label":"Ephemeral","value":"5"},{"label":"Dessert Pie","value":"6"},{"label":"Bottled Drinks","value":"9"},{"label":"Pizza","value":"10"},{"label":"Rainbowl ","value":"11"},{"label":"In house artisan butter","value":"12"},{"label":"Special Occasion","value":"13"},{"label":"Coffee","value":"14"},{"label":"Specialty Chocolates ","value":"15"},{"label":"Japanese","value":"16"},{"label":"Specialty Tea","value":"17"},{"label":"Smoothie","value":"18"},{"label":"Bubbly","value":"19"}]